featureflagger/__init__.py
featureflagger/criteria.py
featureflagger/features.py
featureflagger/guards/criticality.py
featureflagger/protocol.py
featureflagger-0.1.0.dist-info/METADATA
featureflagger-0.1.0.dist-info/WHEEL
featureflagger-0.1.0.dist-info/RECORD
