Metadata-Version: 2.1
Name: featureflagger
Version: 0.1.0
Summary: A flexible and extensible feature flagging library
License: LGPL-3.0-or-later
Author: João Santos
Author-email: jmcs@jsantos.eu
Requires-Python: >=3.8,<4.0
Classifier: License :: OSI Approved :: GNU Lesser General Public License v3 or later (LGPLv3+)
Classifier: Programming Language :: Python :: 3
Classifier: Programming Language :: Python :: 3.8
Classifier: Programming Language :: Python :: 3.9
Classifier: Programming Language :: Python :: 3.10
Classifier: Programming Language :: Python :: 3.11
Classifier: Programming Language :: Python :: 3.12
